MANIFEST.in
README.txt
README.txt.in
generate_readme.py
setup.cfg
setup.py
docs/HISTORY.txt
rbco/__init__.py
rbco.nautilusscripts.egg-info/PKG-INFO
rbco.nautilusscripts.egg-info/SOURCES.txt
rbco.nautilusscripts.egg-info/dependency_links.txt
rbco.nautilusscripts.egg-info/entry_points.txt
rbco.nautilusscripts.egg-info/namespace_packages.txt
rbco.nautilusscripts.egg-info/not-zip-safe
rbco.nautilusscripts.egg-info/requires.txt
rbco.nautilusscripts.egg-info/top_level.txt
rbco/nautilusscripts/PyZenity.py
rbco/nautilusscripts/__init__.py
rbco/nautilusscripts/doc.py
rbco/nautilusscripts/fileinfo.py
rbco/nautilusscripts/install.py
rbco/nautilusscripts/misc.py
rbco/nautilusscripts/nautilus.py
rbco/nautilusscripts/rename.py
rbco/nautilusscripts/text.py
rbco/nautilusscripts/util.py
rbco/nautilusscripts/wrapper.py