Metadata-Version: 1.1
Name: rbco.nautilusscripts
Version: 0.8
Summary: A set of scripts for Nautilus, the Gnome file manager application.
Home-page: UNKNOWN
Author: Rafael Oliveira
Author-email: rafaelbco@gmail.com
License: LGPL
Keywords: linux gnome
Platform: UNKNOWN
Classifier: Programming Language :: Python
Classifier: Topic :: Software Development :: Libraries :: Python Modules
